ckanext/__init__.py
ckanext/latex/__init__.py
ckanext/latex/plugin.py
ckanext/latex/assets/script.js
ckanext/latex/assets/style.css
ckanext/latex/assets/webassets.yml
ckanext/latex/assets/scripts/latex-parse-display.js
ckanext/latex/assets/scripts/latex-parse-form.js
ckanext/latex/assets/scripts/vendor/auto-render.min.js
ckanext/latex/assets/scripts/vendor/katex.js
ckanext/latex/assets/styles/latex.css
ckanext/latex/assets/styles/vendor/katex.css
ckanext/latex/templates/page.html
ckanext/latex/templates/scheming/display_snippets/latex.html
ckanext/latex/templates/scheming/form_snippets/latex.html
ckanext/latex/theme/form.less
ckanext/latex/theme/latex.less
ckanext/latex/theme/variables.less
ckanext_latex-1.0.1.dist-info/LICENSE
ckanext_latex-1.0.1.dist-info/METADATA
ckanext_latex-1.0.1.dist-info/WHEEL
ckanext_latex-1.0.1.dist-info/entry_points.txt
ckanext_latex-1.0.1.dist-info/top_level.txt
ckanext_latex-1.0.1.dist-info/RECORD
