Metadata-Version: 2.1
Name: ckanext-latex
Version: 1.0.1
Summary: LaTeX syntax support for form and display
Author-email: DataShades <datashades@linkdigital.com.au>, Oleksandr Cherniavskyi <mutantsan@gmail.com>
Maintainer-email: DataShades <datashades@linkdigital.com.au>
Project-URL: Homepage, https://github.com/DataShades/ckanext-latex
Classifier: Programming Language :: Python :: 3
Classifier: License :: OSI Approved :: GNU Affero General Public License v3 or later (AGPLv3+)
Classifier: Operating System :: OS Independent
Requires-Python: >=3.8
License-File: LICENSE
Provides-Extra: dev
Requires-Dist: pytest-ckan ; extra == 'dev'
Requires-Dist: ckanext-toolbelt ; extra == 'dev'
Requires-Dist: requests-mock ; extra == 'dev'
Provides-Extra: test
Requires-Dist: pytest-ckan ; extra == 'test'
Requires-Dist: ckanext-toolbelt ; extra == 'test'
Requires-Dist: requests-mock ; extra == 'test'
